odd_dbt/__init__.py
odd_dbt/__version__.py
odd_dbt/app.py
odd_dbt/config.py
odd_dbt/domain/__init__.py
odd_dbt/domain/cli_args.py
odd_dbt/domain/context.py
odd_dbt/domain/credentials.py
odd_dbt/domain/manifest.py
odd_dbt/domain/model.py
odd_dbt/domain/project.py
odd_dbt/domain/result.py
odd_dbt/domain/run_results.py
odd_dbt/domain/source.py
odd_dbt/errors.py
odd_dbt/libs/__init__.py
odd_dbt/libs/dbt.py
odd_dbt/libs/odd.py
odd_dbt/logger.py
odd_dbt/mapper/__init__.py
odd_dbt/mapper/generator.py
odd_dbt/mapper/helpers.py
odd_dbt/mapper/lineage.py
odd_dbt/mapper/metadata.py
odd_dbt/mapper/status_reason.py
odd_dbt/mapper/test_results.py
odd_dbt/mapper/types.py
odd_dbt/service/__init__.py
odd_dbt/service/dbt.py
odd_dbt/service/odd.py
odd_dbt/utils/__init__.py
odd_dbt-0.2.13.dist-info/entry_points.txt
odd_dbt-0.2.13.dist-info/LICENSE
odd_dbt-0.2.13.dist-info/WHEEL
odd_dbt-0.2.13.dist-info/METADATA
odd_dbt-0.2.13.dist-info/RECORD
