Metadata-Version: 2.1
Name: odd-dbt
Version: 0.2.13
Summary: OpenDataDiscovery Action for dbt
License: Apache-2.0
Keywords: Open Data Discovery,dbt,Metadata,Data Discovery,Data Observability
Author: Mateusz Kulas
Author-email: mkulas@provectus.com
Requires-Python: >=3.9,<4.0
Classifier: License :: OSI Approved :: Apache Software License
Classifier: Programming Language :: Python :: 3
Classifier: Programming Language :: Python :: 3.9
Classifier: Programming Language :: Python :: 3.10
Classifier: Programming Language :: Python :: 3.11
Requires-Dist: dbt-postgres (>=1.6.2,<2.0.0)
Requires-Dist: dbt-snowflake (>=1.6.2,<2.0.0)
Requires-Dist: funcy (>=2.0,<3.0)
Requires-Dist: loguru (>=0.7.2,<0.8.0)
Requires-Dist: odd-models (>=2.0.50,<3.0.0)
Requires-Dist: oddrn-generator (>=0.1.102,<0.2.0)
Requires-Dist: psycopg2-binary (>=2.9.6,<3.0.0)
Requires-Dist: sqlalchemy (>=2.0.31,<3.0.0)
Requires-Dist: typer[all] (>=0.7.0,<0.8.0)
